{
	"version": 1,
	"base_image": "codeocean/mambaforge3:24.5.0-0-python3.12.4-ubuntu22.04",
	"post_install": true,
	"options": {
		"registry_host_arg": true,
		"git_ask_pass": true,
		"mount_secrets": true
	},
	"installers": {
		"pip": {
			"packages": [
				{
					"name": "boto3",
					"version": "1.42.30"
				},
				{
					"name": "git+https://github.com/AllenNeuralDynamics/analysis-pipeline-utils#egg=analysis-pipeline-utils",
					"version": "0fb2240751168f5a32b19ba3c0b9712c9f7f6887"
				},
				{
					"name": "pydantic-settings",
					"version": "2.9.1"
				},
				{
					"name": "s3fs",
					"version": "2026.1.0"
				}
			],
			"options": {},
			"pre_install_options": {}
		}
	}
}